Metadata-Version: 1.1
Name: wagtail-react-streamfield-django-3
Version: 1.3.5
Summary: The brand new Wagtail StreamField!
Home-page: https://github.com/mariod3w/wagtail-react-streamfield
Author: Mario Perdomo
Author-email: mariod3w@gmail.com
License: BSD
Platform: UNKNOWN
Classifier: Development Status :: 5 - Production/Stable
Classifier: Framework :: Django
Classifier: Framework :: Wagtail :: 2
Classifier: Intended Audience :: Developers
Classifier: License :: OSI Approved :: BSD License
Classifier: Operating System :: OS Independent
Classifier: Programming Language :: Python
Classifier: Topic :: Internet :: WWW/HTTP
